panda_agi/__init__.py
panda_agi/client/__init__.py
panda_agi/client/agent.py
panda_agi/client/callbacks.py
panda_agi/client/event_manager.py
panda_agi/client/models.py
panda_agi/client/panda_agi_client.py
panda_agi/client/state.py
panda_agi/client/token_processor.py
panda_agi/envs/__init__.py
panda_agi/envs/base_env.py
panda_agi/envs/docker_env.py
panda_agi/envs/e2b_env.py
panda_agi/envs/local_env.py
panda_agi/handlers/README.md
panda_agi/handlers/__init__.py
panda_agi/handlers/base_handler.py
panda_agi/handlers/logs_handler.py
panda_agi/tools/__init__.py
panda_agi/tools/base.py
panda_agi/tools/connection.py
panda_agi/tools/custom_tool_executor.py
panda_agi/tools/custom_tools.py
panda_agi/tools/file_system.py
panda_agi/tools/image.py
panda_agi/tools/notification.py
panda_agi/tools/registry.py
panda_agi/tools/shell.py
panda_agi/tools/skills.py
panda_agi/tools/web.py
panda_agi/tools/custom_tools_ops/__init__.py
panda_agi/tools/custom_tools_ops/custom_tools.py
panda_agi/tools/file_system_ops/__init__.py
panda_agi/tools/file_system_ops/file_ops.py
panda_agi/tools/file_system_ops/shell_ops.py
panda_agi/tools/file_system_ops/utils.py
panda_agi/tools/skills_ops/__init__.py
panda_agi/tools/skills_ops/skills.py
panda_agi/tools/web_ops/beautifulsoup.py
panda_agi/tools/web_ops/tavily.py
panda_agi/train/__init__.py
panda_agi/train/collect.py
panda_agi/train/conversation.py
panda_agi/train/training_model.py
panda_agi/train/proxy/anthropic_proxy.py
panda_agi/train/proxy/base_proxy.py
panda_agi/train/proxy/litellm_proxy.py
panda_agi/train/proxy/openai_proxy.py
panda_agi/train/utils/__init__.py
panda_agi/train/utils/logger.py
panda_agi-0.6.2.dist-info/METADATA
panda_agi-0.6.2.dist-info/WHEEL
panda_agi-0.6.2.dist-info/RECORD
