Metadata-Version: 2.4
Name: panda-agi
Version: 0.6.2
Summary: PandaAGI SDK
Author-email: Facundo Nicolas Maidana <facundo@pandas-ai.com>, Gabriele Venturi <gabriele@pandas-ai.com>
License: MIT
Requires-Python: >=3.8
Requires-Dist: beautifulsoup4
Requires-Dist: docker
Requires-Dist: e2b-code-interpreter
Requires-Dist: httpx
Requires-Dist: markdownify
Requires-Dist: pydantic>=2.0.0
Requires-Dist: python-dotenv
Requires-Dist: requests
Requires-Dist: tavily-python
Provides-Extra: dev
Requires-Dist: black; extra == 'dev'
Requires-Dist: flake8; extra == 'dev'
Requires-Dist: pytest; extra == 'dev'
Provides-Extra: e2b
Requires-Dist: e2b-code-interpreter; extra == 'e2b'
